PyKernelLogit/__init__.py
PyKernelLogit/asym_logit.py
PyKernelLogit/base_multinomial_cm_v2.py
PyKernelLogit/bootstrap.py
PyKernelLogit/bootstrap_abc.py
PyKernelLogit/bootstrap_calcs.py
PyKernelLogit/bootstrap_mle.py
PyKernelLogit/bootstrap_sampler.py
PyKernelLogit/bootstrap_utils.py
PyKernelLogit/choice_calcs.py
PyKernelLogit/choice_tools.py
PyKernelLogit/clog_log.py
PyKernelLogit/conditional_logit.py
PyKernelLogit/construct_estimator.py
PyKernelLogit/display_names.py
PyKernelLogit/estimation.py
PyKernelLogit/kernel_logistic_regression.py
PyKernelLogit/mixed_logit.py
PyKernelLogit/mixed_logit_calcs.py
PyKernelLogit/nested_choice_calcs.py
PyKernelLogit/nested_logit.py
PyKernelLogit/pylogit.py
PyKernelLogit/scobit.py
PyKernelLogit/uneven_logit.py
pykernellogit-0.1.7.dist-info/LICENSE.txt
pykernellogit-0.1.7.dist-info/METADATA
pykernellogit-0.1.7.dist-info/WHEEL
pykernellogit-0.1.7.dist-info/top_level.txt
pykernellogit-0.1.7.dist-info/zip-safe
pykernellogit-0.1.7.dist-info/RECORD
